csdfgen.cpython-314-darwin.so
libcsdfgen.0.28.1.dylib
libcsdfgen.0.dylib
libcsdfgen.dylib
sdfgen/__init__.py
sdfgen/module.py
sdfgen/py.typed
sdfgen-0.28.1.dist-info/METADATA
sdfgen-0.28.1.dist-info/WHEEL
sdfgen-0.28.1.dist-info/top_level.txt
sdfgen-0.28.1.dist-info/RECORD
