Metadata-Version: 2.4
Name: sdfgen
Version: 0.28.1
Summary: Automating the creation of Microkit System Description Files (SDF)
Home-page: https://github.com/au-ts/microkit_sdf_gen
Dynamic: description
Dynamic: description-content-type
Dynamic: home-page
Dynamic: summary
